[{"objects":[{"name":"floor-copy-copy","material":{"diffuse":[1,1,1],"ambient":[0.3,0.3,0.3],"specular":[0.5,0.5,0.5],"n":"90","shaderType":3,"alpha":1},"type":"plane","position":[48,5.5,62],"scale":[64,1,32],"diffuseTexture":"default.jpg","normalTexture":"defaultNorm.jpg","rotation":[0.9999999999999998,-1.0587911840678754e-22,5.551115123125783e-17,0,-5.551115123125783e-17,0.0000023267948965066668,0.9999999999972926,0,0,-0.9999999999972927,0.0000023267948965066676,0,0,0,0,1],"parent":null,"model":null},{"name":"floor-copy-copy-copy-copy-copy-copy-copy-copy-copy-copy-copy-copy","material":{"diffuse":[1,1,1],"ambient":[0.3,0.3,0.3],"specular":[0.5,0.5,0.5],"n":"90","shaderType":3,"alpha":1},"type":"plane","position":[0,5.5,318],"scale":[256,1,32],"diffuseTexture":"default.jpg","normalTexture":"defaultNorm.jpg","rotation":[0.9999999999999998,-1.0587911840678754e-22,5.551115123125783e-17,0,-5.551115123125783e-17,0.0000023267948965066668,0.9999999999972926,0,0,-0.9999999999972927,0.0000023267948965066676,0,0,0,0,1],"parent":null,"model":null},{"name":"walls-copy-copy","material":{"diffuse":[0.5882,0.5882,0.5882],"ambient":[0.3,0.3,0.3],"specular":[0.5,0.5,0.5],"n":10.000002,"shaderType":1,"alpha":1},"type":"cube","position":[-320.5,30,337],"scale":[8,128,512],"diffuseTexture":"default.jpg","normalTexture":"defaultNorm.jpg","rotation":[0.000002326794896478912,0,-0.9999999999972927,0,0,1,0,0,0.9999999999972927,0,0.000002326794896478912,0,0,0,0,1],"parent":null,"model":null},{"name":"walls-copy","material":{"diffuse":[0.5882,0.5882,0.5882],"ambient":[0.3,0.3,0.3],"specular":[0.5,0.5,0.5],"n":10.000002,"shaderType":1,"alpha":1},"type":"cube","position":[-193,30,291.5],"scale":[8,128,256],"diffuseTexture":"default.jpg","normalTexture":"defaultNorm.jpg","rotation":[1,0,0,0,0,1,0,0,0,0,1,0,0,0,0,1],"parent":null,"model":null},{"name":"walls-copy-copy-copy-copy","material":{"diffuse":[0.5882,0.5882,0.5882],"ambient":[0.3,0.3,0.3],"specular":[0.5,0.5,0.5],"n":10.000002,"shaderType":1,"alpha":1},"type":"cube","position":[-320.5,30,-171],"scale":[8,128,512],"diffuseTexture":"default.jpg","normalTexture":"defaultNorm.jpg","rotation":[0.000002326794896478912,0,-0.9999999999972927,0,0,1,0,0,0.9999999999972927,0,0.000002326794896478912,0,0,0,0,1],"parent":null,"model":null},{"name":"floor-copy-copy-copy-copy-copy-copy-copy-copy","material":{"diffuse":[1,1,1],"ambient":[0.3,0.3,0.3],"specular":[0.5,0.5,0.5],"n":"90","shaderType":3,"alpha":1},"type":"plane","position":[128,-2,-200],"scale":[128,1,256],"diffuseTexture":"default.jpg","normalTexture":"defaultNorm.jpg","rotation":[0.000002326794896478912,0,-0.9999999999972927,0,0,1,0,0,0.9999999999972927,0,0.000002326794896478912,0,0,0,0,1],"parent":null,"model":null},{"name":"floor-copy-copy-copy-copy-copy-copy-copy","material":{"diffuse":[1,1,1],"ambient":[0.3,0.3,0.3],"specular":[0.5,0.5,0.5],"n":"90","shaderType":3,"alpha":1},"type":"plane","position":[-48,5.5,-62],"scale":[64,1,32],"diffuseTexture":"default.jpg","normalTexture":"defaultNorm.jpg","rotation":[0.9999999999999998,-1.0587911840678754e-22,5.551115123125783e-17,0,-5.551115123125783e-17,0.0000023267948965066668,0.9999999999972926,0,0,-0.9999999999972927,0.0000023267948965066676,0,0,0,0,1],"parent":null,"model":null},{"name":"floor-copy-copy-copy-copy-copy-copy-copy-copy-copy","material":{"diffuse":[1,1,1],"ambient":[0.3,0.3,0.3],"specular":[0.5,0.5,0.5],"n":"90","shaderType":3,"alpha":1},"type":"plane","position":[320,-2,-83],"scale":[1024,1,512],"diffuseTexture":"default.jpg","normalTexture":"defaultNorm.jpg","rotation":[0.0000023267948965899343,-5.733822375591495e-17,0.999999999997292,0,-1.3877787807814457e-17,0.9999999999999998,5.551115123125783e-17,0,-0.9999999999972926,4.894326850640846e-19,0.0000023267948965899343,0,0,0,0,1],"parent":null,"model":null},{"name":"floor-copy-copy-copy-copy","material":{"diffuse":[1,1,1],"ambient":[0.3,0.3,0.3],"specular":[0.5,0.5,0.5],"n":"90","shaderType":3,"alpha":1},"type":"plane","position":[-48,5.5,62],"scale":[64,1,32],"diffuseTexture":"default.jpg","normalTexture":"defaultNorm.jpg","rotation":[0.9999999999999998,-1.0587911840678754e-22,5.551115123125783e-17,0,-5.551115123125783e-17,0.0000023267948965066668,0.9999999999972926,0,0,-0.9999999999972927,0.0000023267948965066676,0,0,0,0,1],"parent":null,"model":null},{"name":"floor","material":{"diffuse":[1,1,1],"ambient":[0.3,0.3,0.3],"specular":[0.5,0.5,0.5],"n":"90","shaderType":3,"alpha":1},"type":"plane","position":[0,-2,0],"scale":[128,1,256],"diffuseTexture":"default.jpg","normalTexture":"defaultNorm.jpg","rotation":[1,0,0,0,0,1,0,0,0,0,1,0,0,0,0,1],"parent":null,"model":null},{"name":"floor-copy-copy-copy-copy-copy","material":{"diffuse":[1,1,1],"ambient":[0.3,0.3,0.3],"specular":[0.5,0.5,0.5],"n":"90","shaderType":3,"alpha":1},"type":"plane","position":[0,-2,-190],"scale":[512,1,256],"diffuseTexture":"default.jpg","normalTexture":"defaultNorm.jpg","rotation":[0.0000023267948965899343,-5.733822375591495e-17,0.999999999997292,0,-1.3877787807814457e-17,0.9999999999999998,5.551115123125783e-17,0,-0.9999999999972926,4.894326850640846e-19,0.0000023267948965899343,0,0,0,0,1],"parent":null,"model":null},{"name":"floor-copy-copy-copy-copy-copy-copy-copy-copy-copy-copy-copy-copy-copy","material":{"diffuse":[1,1,1],"ambient":[0.3,0.3,0.3],"specular":[0.5,0.5,0.5],"n":"90","shaderType":3,"alpha":1},"type":"plane","position":[64,5.5,190],"scale":[512,1,32],"diffuseTexture":"default.jpg","normalTexture":"defaultNorm.jpg","rotation":[0.0000023267948963956453,0.000002326794896555879,0.9999999999945854,0,-0.9999999999972924,5.414141023837552e-12,0.0000023267948964511564,0,1.1102230246251565e-16,-0.9999999999972926,0.0000023267948965344223,0,0,0,0,1],"parent":null,"model":null},{"name":"floor-copy-copy-copy-copy-copy-copy","material":{"diffuse":[1,1,1],"ambient":[0.3,0.3,0.3],"specular":[0.5,0.5,0.5],"n":"90","shaderType":3,"alpha":1},"type":"plane","position":[48,5.5,-62],"scale":[64,1,32],"diffuseTexture":"default.jpg","normalTexture":"defaultNorm.jpg","rotation":[0.9999999999999998,-1.0587911840678754e-22,5.551115123125783e-17,0,-5.551115123125783e-17,0.0000023267948965066668,0.9999999999972926,0,0,-0.9999999999972927,0.0000023267948965066676,0,0,0,0,1],"parent":null,"model":null},{"name":"walls","material":{"diffuse":[0.5882,0.5882,0.5882],"ambient":[0.3,0.3,0.3],"specular":[0.5,0.5,0.5],"n":10.000002,"shaderType":1,"alpha":1},"type":"cube","position":[-193,30,-83.5],"scale":[8,128,1024],"diffuseTexture":"default.jpg","normalTexture":"defaultNorm.jpg","rotation":[1,0,0,0,0,1,0,0,0,0,1,0,0,0,0,1],"parent":null,"model":null},{"name":"floor-copy-copy-copy-copy-copy-copy-copy-copy-copy-copy","material":{"diffuse":[1,1,1],"ambient":[0.3,0.3,0.3],"specular":[0.5,0.5,0.5],"n":"90","shaderType":3,"alpha":1},"type":"plane","position":[-128,-2,200],"scale":[128,1,256],"diffuseTexture":"default.jpg","normalTexture":"defaultNorm.jpg","rotation":[0.000002326794896478912,0,-0.9999999999972927,0,0,1,0,0,0.9999999999972927,0,0.000002326794896478912,0,0,0,0,1],"parent":null,"model":null},{"name":"walls-copy-copy-copy","material":{"diffuse":[0.5882,0.5882,0.5882],"ambient":[0.3,0.3,0.3],"specular":[0.5,0.5,0.5],"n":10.000002,"shaderType":1,"alpha":1},"type":"cube","position":[-444.5,30,79.5],"scale":[8,128,1024],"diffuseTexture":"default.jpg","normalTexture":"defaultNorm.jpg","rotation":[0.9999999999999996,0,-8.326672684688674e-17,0,0,1,0,0,8.326672684688674e-17,0,0.9999999999999996,0,0,0,0,1],"parent":null,"model":null},{"name":"floor-copy-copy-copy-copy-copy-copy-copy-copy-copy-copy-copy","material":{"diffuse":[1,1,1],"ambient":[0.3,0.3,0.3],"specular":[0.5,0.5,0.5],"n":"90","shaderType":3,"alpha":1},"type":"plane","position":[-319,-2,83],"scale":[1024,1,512],"diffuseTexture":"default.jpg","normalTexture":"defaultNorm.jpg","rotation":[0.0000023267948965899343,-5.733822375591495e-17,0.999999999997292,0,-1.3877787807814457e-17,0.9999999999999998,5.551115123125783e-17,0,-0.9999999999972926,4.894326850640846e-19,0.0000023267948965899343,0,0,0,0,1],"parent":null,"model":null},{"name":"walls-copy-copy-copy-copy-copy","material":{"diffuse":[0.5882,0.5882,0.5882],"ambient":[0.3,0.3,0.3],"specular":[0.5,0.5,0.5],"n":10.000002,"shaderType":1,"alpha":1},"type":"cube","position":[-127,30,229.5],"scale":[8,128,256],"diffuseTexture":"default.jpg","normalTexture":"defaultNorm.jpg","rotation":[0.0000023267948965066676,0,-0.9999999999972927,0,-1.6653345369377348e-16,0.9999999999999998,1.0587911840678754e-22,0,0.9999999999972926,-5.551115123125783e-17,0.0000023267948965066668,0,0,0,0,1],"parent":null,"model":null},{"name":"pillars","material":{"diffuse":[0.5882,0.5882,0.5882],"ambient":[0.3,0.3,0.3],"specular":[0.5,0.5,0.5],"n":10.000002,"shaderType":1,"alpha":1},"type":"cube","position":[-13.5,5.5,-19],"scale":[4,32,4],"diffuseTexture":"default.jpg","normalTexture":"defaultNorm.jpg","rotation":[1,0,0,0,0,1,0,0,0,0,1,0,0,0,0,1],"parent":null,"model":null},{"name":"pillars-copy","material":{"diffuse":[0.5882,0.5882,0.5882],"ambient":[0.3,0.3,0.3],"specular":[0.5,0.5,0.5],"n":10.000002,"shaderType":1,"alpha":1},"type":"cube","position":[15,5.5,19],"scale":[4,32,4],"diffuseTexture":"default.jpg","normalTexture":"defaultNorm.jpg","rotation":[1,0,0,0,0,1,0,0,0,0,1,0,0,0,0,1],"parent":null,"model":null},{"name":"floor-copy-copy-copy","material":{"diffuse":[1,1,1],"ambient":[0.3,0.3,0.3],"specular":[0.5,0.5,0.5],"n":"90","shaderType":3,"alpha":1},"type":"plane","position":[0,-2,190],"scale":[512,1,256],"diffuseTexture":"default.jpg","normalTexture":"defaultNorm.jpg","rotation":[0.0000023267948965899343,-5.733822375591495e-17,0.999999999997292,0,-1.3877787807814457e-17,0.9999999999999998,5.551115123125783e-17,0,-0.9999999999972926,4.894326850640846e-19,0.0000023267948965899343,0,0,0,0,1],"parent":null,"model":null},{"name":"walls-copy-copy-copy-copy-copy-copy","material":{"diffuse":[0.5882,0.5882,0.5882],"ambient":[0.3,0.3,0.3],"specular":[0.5,0.5,0.5],"n":10.000002,"shaderType":1,"alpha":1},"type":"cube","position":[-127,30,170],"scale":[8,128,256],"diffuseTexture":"default.jpg","normalTexture":"defaultNorm.jpg","rotation":[0.0000023267948965066676,0,-0.9999999999972927,0,-1.6653345369377348e-16,0.9999999999999998,1.0587911840678754e-22,0,0.9999999999972926,-5.551115123125783e-17,0.0000023267948965066668,0,0,0,0,1],"parent":null,"model":null},{"name":"pillar-1","material":{"diffuse":[0.5882,0.5882,0.5882],"ambient":[0.3,0.3,0.3],"specular":[0.5,0.5,0.5],"n":10.000002,"shaderType":2,"alpha":1},"type":"mesh","position":[-329.5,22,255],"scale":[256,256,256],"diffuseTexture":"Indian_Pillar.mtl","normalTexture":"defaultNorm.jpg","rotation":[-1,0,-0.00000453837265013135,0,0,1,0,0,0.00000453837265013135,0,-1,0,0,0,0,1],"parent":null,"model":"Indian_Temple_Pillar.obj"},{"name":"torch-far-1","material":{"diffuse":[0.5882,0.5882,0.5882],"ambient":[0.3,0.3,0.3],"specular":[0.5,0.5,0.5],"n":10.000002,"shaderType":2,"alpha":1},"type":"mesh","position":[-435.5,23.5,280],"scale":[32,16,32],"diffuseTexture":"torch.mtl","normalTexture":"defaultNorm.jpg","rotation":[1.0000000000102913,0,-1.1521714263218463e-7,0,0,1,0,0,1.1521714263218463e-7,0,1.0000000000102913,0,0,0,0,1],"parent":null,"model":"torch.obj"},{"name":"torch-far-2","material":{"diffuse":[0.5882,0.5882,0.5882],"ambient":[0.3,0.3,0.3],"specular":[0.5,0.5,0.5],"n":10.000002,"shaderType":2,"alpha":1},"type":"mesh","position":[-435.5,23.5,200.5],"scale":[32,16,32],"diffuseTexture":"torch.mtl","normalTexture":"defaultNorm.jpg","rotation":[1.0000000000102913,0,-1.1521714263218463e-7,0,0,1,0,0,1.1521714263218463e-7,0,1.0000000000102913,0,0,0,0,1],"parent":null,"model":"torch.obj"},{"name":"torch-far-3","material":{"diffuse":[0.5882,0.5882,0.5882],"ambient":[0.3,0.3,0.3],"specular":[0.5,0.5,0.5],"n":10.000002,"shaderType":2,"alpha":1},"type":"mesh","position":[-435.5,23.5,100],"scale":[32,16,32],"diffuseTexture":"torch.mtl","normalTexture":"defaultNorm.jpg","rotation":[1.0000000000102913,0,-1.1521714263218463e-7,0,0,1,0,0,1.1521714263218463e-7,0,1.0000000000102913,0,0,0,0,1],"parent":null,"model":"torch.obj"},{"name":"torch-far-4","material":{"diffuse":[0.5882,0.5882,0.5882],"ambient":[0.3,0.3,0.3],"specular":[0.5,0.5,0.5],"n":10.000002,"shaderType":2,"alpha":1},"type":"mesh","position":[-435.5,23.5,0],"scale":[32,16,32],"diffuseTexture":"torch.mtl","normalTexture":"defaultNorm.jpg","rotation":[1.0000000000102913,0,-1.1521714263218463e-7,0,0,1,0,0,1.1521714263218463e-7,0,1.0000000000102913,0,0,0,0,1],"parent":null,"model":"torch.obj"},{"name":"torch-far-5","material":{"diffuse":[0.5882,0.5882,0.5882],"ambient":[0.3,0.3,0.3],"specular":[0.5,0.5,0.5],"n":10.000002,"shaderType":2,"alpha":1},"type":"mesh","position":[-435.5,23.5,-100],"scale":[32,16,32],"diffuseTexture":"torch.mtl","normalTexture":"defaultNorm.jpg","rotation":[1.0000000000102913,0,-1.1521714263218463e-7,0,0,1,0,0,1.1521714263218463e-7,0,1.0000000000102913,0,0,0,0,1],"parent":null,"model":"torch.obj"},{"name":"torch-enter-1","material":{"diffuse":[0.5882,0.5882,0.5882],"ambient":[0.3,0.3,0.3],"specular":[0.5,0.5,0.5],"n":10.000002,"shaderType":2,"alpha":1},"type":"mesh","position":[-201.5,23.5,100],"scale":[32,16,32],"diffuseTexture":"torch.mtl","normalTexture":"defaultNorm.jpg","rotation":[-1,0,-0.00000453837265013135,0,0,1,0,0,0.00000453837265013135,0,-1,0,0,0,0,1],"parent":null,"model":"torch.obj"},{"name":"torch-enter-2","material":{"diffuse":[0.5882,0.5882,0.5882],"ambient":[0.3,0.3,0.3],"specular":[0.5,0.5,0.5],"n":10.000002,"shaderType":2,"alpha":1},"type":"mesh","position":[-201.5,23.5,0],"scale":[32,16,32],"diffuseTexture":"torch.mtl","normalTexture":"defaultNorm.jpg","rotation":[-1,0,-0.00000453837265013135,0,0,1,0,0,0.00000453837265013135,0,-1,0,0,0,0,1],"parent":null,"model":"torch.obj"},{"name":"torch-enter-3","material":{"diffuse":[0.5882,0.5882,0.5882],"ambient":[0.3,0.3,0.3],"specular":[0.5,0.5,0.5],"n":10.000002,"shaderType":2,"alpha":1},"type":"mesh","position":[-201.5,23.5,-100],"scale":[32,16,32],"diffuseTexture":"torch.mtl","normalTexture":"defaultNorm.jpg","rotation":[-1,0,-0.00000453837265013135,0,0,1,0,0,0.00000453837265013135,0,-1,0,0,0,0,1],"parent":null,"model":"torch.obj"},{"name":"torch-enter-4","material":{"diffuse":[0.5882,0.5882,0.5882],"ambient":[0.3,0.3,0.3],"specular":[0.5,0.5,0.5],"n":10.000002,"shaderType":2,"alpha":1},"type":"mesh","position":[-201.5,23.5,280],"scale":[32,16,32],"diffuseTexture":"torch.mtl","normalTexture":"defaultNorm.jpg","rotation":[-1,0,-0.00000453837265013135,0,0,1,0,0,0.00000453837265013135,0,-1,0,0,0,0,1],"parent":null,"model":"torch.obj"},{"name":"pillar-2","material":{"diffuse":[0.5882,0.5882,0.5882],"ambient":[0.3,0.3,0.3],"specular":[0.5,0.5,0.5],"n":10.000002,"shaderType":2,"alpha":1},"type":"mesh","position":[-329.5,22,-25],"scale":[256,256,256],"diffuseTexture":"Indian_Pillar.mtl","normalTexture":"defaultNorm.jpg","rotation":[-1,0,-0.00000453837265013135,0,0,1,0,0,0.00000453837265013135,0,-1,0,0,0,0,1],"parent":null,"model":"Indian_Temple_Pillar.obj"},{"name":"skeleton-enter-left","material":{"diffuse":[0.5882,0.5882,0.5882],"ambient":[0.3,0.3,0.3],"specular":[0.5,0.5,0.5],"n":10.000002,"shaderType":2,"alpha":1},"type":"mesh","position":[-212.5,18.5,150],"scale":[16,16,16],"diffuseTexture":"skeleton3.mtl","normalTexture":"defaultNorm.jpg","rotation":[1.000000000010291,0,-1.1521714285422924e-7,0,0,1,0,0,1.1521714285422924e-7,0,1.000000000010291,0,0,0,0,1],"parent":null,"model":"skeleton3.obj"},{"name":"skeleton-enter-right","material":{"diffuse":[0.5882,0.5882,0.5882],"ambient":[0.3,0.3,0.3],"specular":[0.5,0.5,0.5],"n":10.000002,"shaderType":2,"alpha":1},"type":"mesh","position":[-212.5,18.5,250],"scale":[16,16,16],"diffuseTexture":"skeleton3.mtl","normalTexture":"defaultNorm.jpg","rotation":[-0.9999999999999991,0,-0.000004538372650297884,0,0,1,0,0,0.000004538372650297884,0,-0.9999999999999991,0,0,0,0,1],"parent":null,"model":"skeleton3.obj"}],"pointLights":[{"name":"pointLight1","colour":[1,1,1],"position":[-0.5,5,0],"strength":11,"quadratic":0.035,"linear":0.09,"constant":1,"nearPlane":0.5,"farPlane":600,"shadow":0},{"name":"light2","colour":[1,1,1],"position":[325,30,0],"strength":33,"quadratic":0.035,"linear":0.09,"constant":1,"nearPlane":0.5,"farPlane":600,"shadow":1},{"name":"light3","colour":[1,1,1],"position":[-323,54,-92.5],"strength":83,"quadratic":0.035,"linear":0.09,"constant":1,"nearPlane":0.5,"farPlane":600,"shadow":0},{"name":"light4","colour":[1,1,1],"position":[1,10,160],"strength":33,"quadratic":0.035,"linear":0.09,"constant":1,"nearPlane":0.5,"farPlane":600,"shadow":0},{"name":"light5","colour":[1,1,1],"position":[-336.5,42.5,341],"strength":81,"quadratic":0.035,"linear":0.09,"constant":1,"nearPlane":0.5,"farPlane":600,"shadow":0},{"name":"light6","colour":[1,1,1],"position":[-338,56.5,129],"strength":85,"quadratic":0.035,"linear":0.09,"constant":1,"nearPlane":0.5,"farPlane":600,"shadow":0}],"settings":{"camera":{"name":"mainCamera","position":[-511.6697692871094,226.1238555908203,228.12307739257812],"front":[0.594345801572181,-0.6971651239948821,-0.40089132946313805],"up":[0,30,0],"pitch":-44.199999999999704,"yaw":-1113.9999999998051,"roll":0,"moveSpeed":10,"move":false,"canvasFocused":false,"rateX":0,"rateY":0,"keyboard":{"d":false,"s":false,"a":false,"w":false},"viewMatrix":{"0":0.5591862201690674,"1":0.5779708623886108,"2":-0.5943571329116821,"3":0,"4":0,"5":0.7169203758239746,"6":0.6971550583839417,"7":0,"8":0.8290420770645142,"9":-0.3898395001888275,"10":0.4008920192718506,"11":0,"12":96.99506378173828,"13":222.54881286621094,"14":-553.210693359375,"15":1},"sensitivity":0.4},"backgroundColor":[1,1,1]}}]